<?xml version="1.0" encoding="utf-8"?>
<extension type="module" version="2.5" method="upgrade">
    <name>MOD_SIMPLELISTS_INDEX</name>
    <author>Yireo</author>
    <creationDate>June 2016</creationDate>
    <license>http://www.gnu.org/licenses/gpl-2.0.html GNU/GPL</license>
    <authorEmail>info@yireo.com</authorEmail>
    <authorUrl>https://www.yireo.com/</authorUrl>
    <version>1.8.0</version>
    <description>MOD_SIMPLELISTS_INDEX_DESC</description>

    <files folder="site">
        <filename module="mod_simplelists_index">mod_simplelists_index.php</filename>
        <filename>helper.php</filename>
        <folder>tmpl</folder>
        <folder>language</folder>
    </files>

    <files>
        <filename>mod_simplelists_index.xml</filename>
    </files>

    <languages folder="site/language/en-GB">
        <language tag="en-GB">en-GB.mod_simplelists_index.ini</language>
        <language tag="en-GB">en-GB.mod_simplelists_index.sys.ini</language>
    </languages>

    <updateservers>
        <server type="extension" priority="1" name="mod_simplelists_index">
            https://www.yireo.com/updates/mod_simplelists_index.xml
        </server>
    </updateservers>
</extension>
